tests/__init__.py
tests/vantage6/__init__.py
tests/vantage6/common/__init__.py
tests/vantage6/common/docker/__init__.py
tests/vantage6/common/docker/test_addons.py
vantage6/common/__build__
vantage6/common/__init__.py
vantage6/common/_version.py
vantage6/common/colors.py
vantage6/common/configuration_manager.py
vantage6/common/context.py
vantage6/common/encryption.py
vantage6/common/enum.py
vantage6/common/exceptions.py
vantage6/common/globals.py
vantage6/common/log.py
vantage6/common/serialization.py
vantage6/common/task_status.py
vantage6/common/utest.py
vantage6/common/client/client_base.py
vantage6/common/client/deserialization.py
vantage6/common/client/node_client.py
vantage6/common/client/utils.py
vantage6/common/docker/__init__.py
vantage6/common/docker/addons.py
vantage6/common/docker/network_manager.py
vantage6_common_blob-4.10.2.dist-info/METADATA
vantage6_common_blob-4.10.2.dist-info/WHEEL
vantage6_common_blob-4.10.2.dist-info/top_level.txt
vantage6_common_blob-4.10.2.dist-info/RECORD
